{
  "categories": [
    {
      "title": "Vegetables",
      "img": "/images/veggies.png",
      "id": "33c3"
    },
    {
      "title": "Fruits",
      "img": "/images/fruits.png",
      "id": "7541"
    },
    {
      "title": "Dairy",
      "img": "/images/dairy.png",
      "id": "d9e9"
    },
    {
      "title": "Grains",
      "img": "/images/grains.png",
      "id": "84a7"
    },
    {
      "title": "Bakery",
      "img": "/images/bakery.png",
      "id": "18a4"
    },
    {
      "title": "Coldrink",
      "img": "/images/cold drinks.png",
      "id": "bbfd"
    },
    {
      "title": "Instant food",
      "img": "/images/instant food.png",
      "id": "c9ae"
    }
  ],
  "products": [
    {
      "title": "Tomato",
      "MRP": 20,
      "img": "/images/tomato.png",
      "category": "Vegetables",
      "qty": 1,
      "id": "e99a"
    },
    {
      "title": "Potato",
      "MRP": 30,
      "img": "/images/potato.png",
      "category": "Vegetables",
      "qty": 1,
      "id": "52a6"
    },
    {
      "title": "Brinjal",
      "MRP": 15,
      "img": "/images/brinjal.jpg",
      "category": "Vegetables",
      "qty": 1,
      "id": "1b48"
    },
    {
      "title": "Capsicum",
      "MRP": 35,
      "img": "/images/capsicum.webp",
      "category": "Vegetables",
      "qty": 1,
      "id": "1cb0"
    },
    {
      "title": "Carrot",
      "MRP": 25,
      "img": "/images/carrot.png",
      "category": "Vegetables",
      "qty": 1,
      "id": "52aa"
    },
    {
      "title": "Chilli",
      "MRP": 25,
      "img": "/images/chili.jpg",
      "category": "Vegetables",
      "qty": 1,
      "id": "6669"
    },
    {
      "title": "cauliflower",
      "MRP": 25,
      "img": "/images/flower.jpg",
      "category": "Vegetables",
      "qty": 1,
      "id": "f3e5"
    },
    {
      "title": "Onion",
      "MRP": 25,
      "img": "/images/onion.png",
      "category": "Vegetables",
      "qty": 1,
      "id": "7e40"
    },
    {
      "title": "lady finger",
      "MRP": 25,
      "img": "/images/ladyfinger.jpg",
      "category": "Vegetables",
      "qty": 1,
      "id": "87b3"
    },
    {
      "title": "Spinach",
      "MRP": 25,
      "img": "/images/spinach.jpg",
      "category": "Vegetables",
      "qty": 1,
      "id": "2d0e"
    },
    {
      "title": "Apple",
      "MRP": 150,
      "img": "/images/apple.png",
      "category": "Fruits",
      "qty": 1,
      "id": "8292"
    },
    {
      "title": "Banana",
      "MRP": 40,
      "img": "/images/banana.png",
      "category": "Fruits",
      "qty": 1,
      "id": "2bb8"
    },
    {
      "title": "Orange",
      "MRP": 80,
      "img": "/images/orange.png",
      "category": "Fruits",
      "qty": 1,
      "id": "0179"
    },
    {
      "title": "Grapes",
      "MRP": 120,
      "img": "/images/graphes.png",
      "category": "Fruits",
      "qty": 1,
      "id": "e050"
    },
    {
      "title": "Mango",
      "MRP": 100,
      "img": "/images/mango.png",
      "category": "Fruits",
      "qty": 1,
      "id": "24fe"
    },
    {
      "title": "Pineapple",
      "MRP": 90,
      "img": "/images/pianapple.jpg",
      "category": "Fruits",
      "qty": 1,
      "id": "0ff6"
    },
    {
      "title": "Papaya",
      "MRP": 60,
      "img": "/images/papaya.jpg",
      "category": "Fruits",
      "qty": 1,
      "id": "2692"
    },
    {
      "title": "Pomegranate",
      "MRP": 150,
      "img": "/images/pomo.jpg",
      "category": "Fruits",
      "qty": 1,
      "id": "4c29"
    },
    {
      "title": "Strawberry",
      "MRP": 180,
      "img": "/images/berry.jpg",
      "category": "Fruits",
      "qty": 1,
      "id": "24b0"
    },
    {
      "title": "Watermelon",
      "MRP": 70,
      "img": "/images/watermelon.jpg",
      "category": "Fruits",
      "qty": 1,
      "id": "74bf"
    },
    {
      "title": "Milk",
      "MRP": 28,
      "img": "/images/milk.png",
      "category": "Dairy",
      "qty": 1,
      "id": "281a"
    },
    {
      "title": "Cheese",
      "MRP": 80,
      "img": "/images/cheese.png",
      "category": "Dairy",
      "qty": 1,
      "id": "0f7d"
    },
    {
      "title": "Butter",
      "MRP": 60,
      "img": "/images/butter.png",
      "category": "Dairy",
      "qty": 1,
      "id": "29c5"
    },
    {
      "title": "Amul Lassi",
      "MRP": 55,
      "img": "/images/lassi.jpg",
      "category": "Dairy",
      "qty": 1,
      "id": "3ee3"
    },
    {
      "title": "Amul Ice Cream",
      "MRP": 250,
      "img": "/images/icecream.avif",
      "category": "Dairy",
      "qty": 1,
      "id": "e090"
    },
    {
      "title": "Britannia Paneer",
      "MRP": 100,
      "img": "/images/paneer.png",
      "category": "Dairy",
      "qty": 1,
      "id": "6ec6"
    },
    {
      "title": "Fresh Cream",
      "MRP": 70,
      "img": "/images/cream.jpg",
      "category": "Dairy",
      "qty": 1,
      "id": "b9b0"
    },
    {
      "title": "Dannon Ghee",
      "MRP": 150,
      "img": "/images/ghee.avif",
      "category": "Dairy",
      "qty": 1,
      "id": "02eb"
    },
    {
      "title": "Amul Masti Curd",
      "MRP": 65,
      "img": "/images/curd.avif",
      "category": "Dairy",
      "qty": 1,
      "id": "bfc5"
    },
    {
      "title": "Mataka Khulfi",
      "MRP": 60,
      "img": "/images/kulfi.jpg",
      "category": "Dairy",
      "qty": 1,
      "id": "d367"
    },
    {
      "title": "Rice",
      "MRP": 60,
      "img": "/images/rice.png",
      "category": "Grains",
      "qty": 1,
      "id": "bde6"
    },
    {
      "title": "Samrat Wheat flour",
      "MRP": 150,
      "img": "/images/wheate.png",
      "category": "Grains",
      "qty": 1,
      "id": "430c"
    },
    {
      "title": "Ashirvaad Besan",
      "MRP": 80,
      "img": "/images/besan.jpg",
      "category": "Grains",
      "qty": 1,
      "id": "afe5"
    },
    {
      "title": "Basmati Rice",
      "MRP": 145,
      "img": "/images/rice.png",
      "category": "Grains",
      "qty": 1,
      "id": "9a95"
    },
    {
      "title": "Quinoa",
      "MRP": 120,
      "img": "/images/quino.jpg",
      "category": "Grains",
      "qty": 1,
      "id": "f873"
    },
    {
      "title": "Raagi maat",
      "MRP": 70,
      "img": "/images/ragi.jpg",
      "category": "Grains",
      "qty": 1,
      "id": "07ea"
    },
    {
      "title": "Maida",
      "MRP": 60,
      "img": "/images/maida.jpg",
      "category": "Grains",
      "qty": 1,
      "id": "55b9"
    },
    {
      "title": "Corn flour",
      "MRP": 55,
      "img": "/images/corn_flour.jpg",
      "category": "Grains",
      "qty": 1,
      "id": "8aba"
    },
    {
      "title": "Barley",
      "MRP": 50,
      "img": "/images/barley.jpg",
      "category": "Grains",
      "qty": 1,
      "id": "6c4d"
    },
    {
      "title": "Brown Rice",
      "MRP": 65,
      "img": "/images/brown rice.png",
      "category": "Grains",
      "qty": 1,
      "id": "8117"
    },
    {
      "title": "Bread",
      "MRP": 40,
      "img": "/images/bread.png",
      "category": "Bakery",
      "qty": 1,
      "id": "7fcc"
    },
    {
      "title": "Bun",
      "MRP": 20,
      "img": "/images/pav.png",
      "category": "Bakery",
      "qty": 1,
      "id": "ae04"
    },
    {
      "title": "Cake_rusk",
      "MRP": 150,
      "img": "/images/cake_rusk.png",
      "category": "Bakery",
      "qty": 1,
      "id": "045c"
    },
    {
      "title": "Brown Bread",
      "MRP": 60,
      "img": "/images/brobread.jpg",
      "category": "Bakery",
      "qty": 1,
      "id": "e22f"
    },
    {
      "title": "Muffin",
      "MRP": 50,
      "img": "/images/muffin.png",
      "category": "Bakery",
      "qty": 1,
      "id": "4ec8"
    },
    {
      "title": "Milk Bread",
      "MRP": 40,
      "img": "/images/bread.png",
      "category": "Bakery",
      "qty": 1,
      "id": "c49d"
    },
    {
      "title": "Brownie",
      "MRP": 30,
      "img": "/images/brownie.avif",
      "category": "Bakery",
      "qty": 1,
      "id": "46da"
    },
    {
      "title": "Burger Buns",
      "MRP": 35,
      "img": "/images/burger_buns.jpg",
      "category": "Bakery",
      "qty": 1,
      "id": "9053"
    },
    {
      "title": "Khari",
      "MRP": 80,
      "img": "/images/khari.jpg",
      "category": "Bakery",
      "qty": 1,
      "id": "6469"
    },
    {
      "title": "Vanilla cupcake",
      "MRP": 120,
      "img": "/images/vanilla_cupcake.png",
      "category": "Bakery",
      "qty": 1,
      "id": "4da0"
    },
    {
      "title": "coco cola",
      "MRP": 40,
      "img": "/images/coca_cola.jpg",
      "category": "Coldrink",
      "qty": 1,
      "id": "3e4a"
    },
    {
      "title": "Maaza",
      "MRP": 40,
      "img": "/images/maaza.jpg",
      "category": "Coldrink",
      "qty": 1,
      "id": "627d"
    },
    {
      "title": "Sprite",
      "MRP": 40,
      "img": "/images/sprite.png",
      "category": "Coldrink",
      "qty": 1,
      "id": "83ad"
    },
    {
      "title": "Fanta",
      "MRP": 35,
      "img": "/images/fanta.png",
      "category": "Coldrink",
      "qty": 1,
      "id": "8269"
    },
    {
      "title": "Slice",
      "MRP": 30,
      "img": "/images/slice.jpg",
      "category": "Coldrink",
      "qty": 1,
      "id": "c233"
    },
    {
      "title": "Pepsi",
      "MRP": 40,
      "img": "/images/pepsi.jpg",
      "category": "Coldrink",
      "qty": 1,
      "id": "b152"
    },
    {
      "title": "Thumbs Up",
      "MRP": 40,
      "img": "/images/thums_up.jpg",
      "category": "Coldrink",
      "qty": 1,
      "id": "c422"
    },
    {
      "title": "Limca",
      "MRP": 35,
      "img": "/images/limca.jpg",
      "category": "Coldrink",
      "qty": 1,
      "id": "a4b2"
    },
    {
      "title": "Appy fizz",
      "MRP": 30,
      "img": "/images/appy_fizz.jpg",
      "category": "Coldrink",
      "qty": 1,
      "id": "9dbc"
    },
    {
      "title": "Mountain Dew",
      "MRP": 40,
      "img": "/images/mountain_dew.jpg",
      "category": "Coldrink",
      "qty": 1,
      "id": "5027"
    },
    {
      "title": "Oats",
      "MRP": 20,
      "img": "/images/oats.jpg",
      "category": "Instant food",
      "qty": 1,
      "id": "8da2"
    },
    {
      "title": "Pasta",
      "MRP": 30,
      "img": "/images/pasta.jpg",
      "category": "Instant food",
      "qty": 1,
      "id": "2085"
    },
    {
      "title": "Soup",
      "MRP": 40,
      "img": "/images/soup.png",
      "category": "Instant food",
      "qty": 1,
      "id": "2d3b"
    },
    {
      "title": "Instant Poha",
      "MRP": 12,
      "img": "/images/poha.jpg",
      "category": "Instant food",
      "qty": 1,
      "id": "9df8"
    },
    {
      "title": "Maggie",
      "MRP": 15,
      "img": "/images/maggie.png",
      "category": "Instant food",
      "qty": 1,
      "id": "c5f2"
    },
    {
      "title": "Sweet Corn Soup",
      "MRP": 25,
      "img": "/images/sweet_corn_soup.jpg",
      "category": "Instant food",
      "qty": 1,
      "id": "82b1"
    },
    {
      "title": "Upma Instant",
      "MRP": 30,
      "img": "/images/upma.jpg",
      "category": "Instant food",
      "qty": 1,
      "id": "efeb"
    },
    {
      "title": "Pasta",
      "MRP": 35,
      "img": "/images/pasta.jpg",
      "category": "Instant food",
      "qty": 1,
      "id": "6479"
    },
    {
      "title": "Tomato Soup",
      "MRP": 50,
      "img": "/images/tomato_soup.jpg",
      "category": "Instant food",
      "qty": 1,
      "id": "fc66"
    },
    {
      "title": "Yippee",
      "MRP": 20,
      "img": "/images/yippee.jpg",
      "category": "Instant food",
      "qty": 1,
      "id": "5309"
    }
  ],
  "cart": []
}